{
  "name": "Esdras",
  "id": "Esdras",
  "order": 15,
  "chapters": {
    "1": {
      "1": "Y EN el primer{H259} año{H8141} de Ciro{H3566} rey{H4428} de Persia{H6539}, para que se cumpliese{H3615} la palabra{H1697} de Jehová{H3068} por boca{H6310} de Jeremías{H3414}, excitó Jehová{H3068} el espíritu{H7307} de Ciro{H3566} rey{H4428} de Persia{H6539}, el cual hizo pasar pregón por todo{H3605} su reino{H4438}, y también{H1571} por escrito{H4385}, diciendo{H559}:",
      "2": "Así{H3541} ha dicho{H559} Ciro{H3566} rey{H4428} de Persia{H6539}: Jehová{H3068} Dios{H430} de los cielos{H8064} me ha dado{H5414} todos{H3605} los reinos{H4467} de la tierra{H776}, y me{H5921} ha mandado{H6485} que le edifique{H1129} casa{H1004} en Jerusalem{H3389}, que{H834} está en Judá{H3063}.",
      "3": "¿Quién hay entre vosotros de todo su{H1931} pueblo{H5971}? Sea{H1961} Dios{H430} con{H5973} él{H1931}, y suba{H5927} á Jerusalem{H3389} que{H834} está en Judá{H3063}, y edifique{H1129} la casa{H1004} á Jehová{H3068} Dios{H430} de Israel{H3478}, (él{H1931} es el Dios{H430},) la cual{H834} está en Jerusalem{H3389}.",
      "4": "Y á cualquiera{H3605} que hubiere quedado{H7604} de todos{H3605} los lugares{H4725} donde{H834} peregrinare, los hombres{H582} de su{H1931} lugar{H4725} le ayuden{H5375} con plata{H3701}, y oro{H2091}, y hacienda{H7399}, y con bestias{H929}; con dones voluntarios{H5071} para la casa{H1004} de Dios{H430}, la cual{H834} está en Jerusalem{H3389}.",
      "5": "Entonces se levantaron{H6965} los cabezas{H7218} de las familias de Judá{H3063} y de Benjamín{H1144}, y los sacerdotes{H3548} y Levitas{H3881}, todos{H3605} aquellos cuyo espíritu{H7307} despertó{H5782} Dios{H430} para subir{H5927} á edificar{H1129} la casa{H1004} de Jehová{H3068}, la cual{H834} está en Jerusalem{H3389}.",
      "6": "Y todos{H3605} los que estaban en sus alrededores{H5439} confortaron{H2388} las manos{H3027} de ellos con vasos{H3627} de plata{H3701} y de oro{H2568}, con hacienda{H7399} y bestias{H929}, y con cosas preciosas{H4030}, á más{H5921} de lo que se ofreció{H5068} voluntariamente.",
      "7": "Y el rey{H4428} Ciro{H3566} sacó{H3318} los vasos{H3627} de la casa{H1004} de Jehová{H3068}, que{H834} Nabucodonosor{H5019} había traspasado{H3318} de Jerusalem{H3389}, y puesto{H5414} en la casa{H1004} de sus dioses{H430}.",
      "8": "Sacólos{H3318} pues Ciro{H3566} rey{H4428} de Persia{H6539}, por{H5921} mano{H3027} de Mitrídates{H4990} tesorero{H1489}, el cual los dió por cuenta{H5608} á Sesbassar{H8339} príncipe{H5387} de Judá{H3063}.",
      "9": "Y esta{H428} es la cuenta{H4557} de ellos: treinta{H7970} tazones{H105} de oro{H2091}, mil{H505} tazones{H105} de plata{H3701}, veinte{H6242} y nueve{H8672} cuchillos{H4252},",
      "10": "Treinta{H7970} tazas{H3713} de oro{H2091}, cuatrocientas{H702} y diez{H6235} otras{H4932} tazas{H3713} de plata{H3701}, y mil{H505} otros{H312} vasos{H3627}.",
      "11": "Todos{H3605} los vasos{H3627} de oro{H2091} y de plata{H3701}, cinco{H2568} mil{H505} y cuatrocientos{H702}{H3967}. Todos{H3605} los hizo llevar{H5927} Sesbassar{H8339} con{H5973} los que subieron{H5927} del cautiverio{H1473} de Babilonia{H894} á Jerusalem{H3389}."
    },
    "2": {
      "1": "Y ESTOS{H428} son los hijos{H1121} de la provincia{H4082} que subieron{H5927} de la cautividad{H7628}, de la transmigración{H1473} que{H834} Nabucodonosor{H5019} rey{H4428} de Babilonia{H894} hizo traspasar á Babilonia{H894}, y que{H834} volvieron{H7725} á Jerusalem{H3389} y á Judá{H3063}, cada uno{H376} á su ciudad{H5892}:",
      "2": "Los cuales vinieron{H935} con{H5973} Zorobabel{H2216}, Jesuá{H3442}, Nehemías{H5166}, Seraías{H8304}, Reelaías{H7480}, Mardochêo{H4782}, Bilsán{H1114}, Mispar{H4558}, Bigvai{H902}, Rehum{H7348} [y] Baana{H1196}. La cuenta{H4557} de los varones{H582} del pueblo{H5971} de Israel{H3478}:",
      "3": "Los hijos{H1121} de Paros{H6551}, dos mil{H505} ciento{H3967} setenta{H7657} y dos{H8147};",
      "4": "Los hijos{H1121} de Sephatías{H8203}, trescientos{H7969}{H3967} setenta{H7657} y dos{H8147};",
      "5": "Los hijos{H1121} de Ara{H733}, setecientos{H7651}{H3967} setenta{H7657} y cinco{H2568};",
      "6": "Los hijos{H1121} de Pahath-moab{H6355}, de los hijos{H1121} de Josué [y] de Joab{H3097}, dos mil{H505} ochocientos{H8083}{H3967} y doce{H8147}{H6240};",
      "7": "Los hijos{H1121} de Elam{H5867}, mil{H505} doscientos{H3967} cincuenta{H2572} y cuatro{H702};",
      "8": "Los hijos{H1121} de Zattu{H2240}, novecientos{H8672}{H3967} cuarenta{H705} y cinco{H2568};",
      "9": "Los hijos{H1121} de Zachâi{H2140}, setecientos{H7651}{H3967} y sesenta{H8346};",
      "10": "Los hijos{H1121} de Bani{H1137}, seiscientos{H8337}{H3967} cuarenta{H705} y dos{H8147};",
      "11": "Los hijos{H1121} de Bebai{H893}, seiscientos{H8337}{H3967} veinte{H6242} y tres{H7969};",
      "12": "Los hijos{H1121} de Azgad{H5803}, mil{H505} doscientos{H3967} veinte{H6242} y dos{H8147};",
      "13": "Los hijos{H1121} de Adonicam{H140}, seiscientos{H8337}{H3967} sesenta{H8346} y seis{H8337};",
      "14": "Los hijos{H1121} de Bigvai{H902}, dos mil{H505} cincuenta{H2572} y seis{H8337};",
      "15": "Los hijos{H1121} de Adin, cuatrocientos{H702}{H3967} cincuenta{H2572} y cuatro{H702};",
      "16": "Los hijos{H1121} de Ater{H333}, de Ezechîas{H2396}, noventa{H8673} y ocho{H8083};",
      "17": "Los hijos{H1121} de Besai{H1209}, trescientos{H7969}{H3967} veinte{H6242} y tres{H7969};",
      "18": "Los hijos{H1121} de Jora{H3139}, ciento{H3967} y doce{H8147}{H6240};",
      "19": "Los hijos{H1121} de Hasum{H2828}, doscientos{H3967} veinte{H6242} y tres{H7969};",
      "20": "Los hijos{H1121} de Gibbar{H1402}, noventa{H8673} y cinco{H2568};",
      "21": "Los hijos{H1121} de Beth-lehem{H1035}, ciento{H3967} veinte{H6242} y tres{H7969};",
      "22": "Los varones{H582} de Nethopha{H5199}, cincuenta{H2572} y seis{H8337};",
      "23": "Los varones{H582} de Anathoth{H6068}, ciento{H3967} veinte{H6242} y ocho{H8083};",
      "24": "Los hijos{H1121} de Asmaveth{H5820}, cuarenta{H705} y dos{H8147};",
      "25": "Los hijos{H1121} de Chîriath-jearim{H7157}, Cephira{H3716}, y Beeroth{H881}, setecientos{H7651}{H3967} cuarenta{H705} y tres{H7969};",
      "26": "Los hijos{H1121} de Rama{H7414} y Gabaa{H1387}, seiscientos{H8337}{H3967} veinte{H6242} y uno{H259};",
      "27": "Los varones{H582} de Michmas{H4363}, ciento{H3967} veinte{H6242} y dos{H8147};",
      "28": "Los varones{H582} de Beth-el{H1008} y Hai{H5857}, doscientos{H3967} veinte{H6242} y tres{H7969};",
      "29": "Los hijos{H1121} de Nebo{H5015}, cincuenta{H2572} y dos{H8147};",
      "30": "Los hijos{H1121} de Magbis{H4019}, ciento{H3967} cincuenta{H2572} y seis{H8337};",
      "31": "Los hijos{H1121} del otro{H312} Elam{H5867}, mil{H505} doscientos{H3967} cincuenta{H2572} y cuatro{H702};",
      "32": "Los hijos{H1121} de Harim{H2766}, trescientos{H7969}{H3967} y veinte{H6242};",
      "33": "Los hijos{H1121} de Lod{H3850}, Hadid{H3865}, y Ono{H2307}, setecientos{H7651} veinte{H6242} y cinco{H2568};",
      "34": "Los hijos{H1121} de Jericó{H3405}, trescientos{H7969}{H3967} cuarenta{H705} y cinco{H2568};",
      "35": "Los hijos{H1121} de Senaa{H5570}, tres{H7969} mil{H505} seiscientos{H8337}{H3967} y treinta{H7970};",
      "36": "Los sacerdotes{H3548}: los hijos{H1121} de Jedaía{H3048}, de la casa{H1004} de Jesuá{H3442}, novecientos{H8672}{H3967} setenta{H7657} y tres{H7969};",
      "37": "Los hijos{H1121} de Immer{H564}, mil{H505} cincuenta{H2572} y dos{H8147};",
      "38": "Los hijos{H1121} de Pashur{H6583}, mil{H505} doscientos{H3967} cuarenta{H705} y siete{H7651};",
      "39": "Los hijos{H1121} de Harim{H2766}, mil{H505} diez{H7651} y siete{H6240}.",
      "40": "Los Levitas{H3881}: los hijos{H1121} de Jesuá{H3442} y de Cadmiel{H6934}, de los hijos{H1121} de Odovías{H1938}, setenta{H7657} y cuatro{H702}.",
      "41": "Los cantores{H7891}: los hijos{H1121} de Asaph{H623}, ciento{H3967} veinte{H6242} y ocho{H8083}.",
      "42": "Los hijos{H1121} de los porteros{H7778}: los hijos{H1121} de Sallum{H7967}, los hijos{H1121} de Ater{H333}, los hijos{H1121} de Talmón{H2929}, los hijos{H1121} de Accub{H6126}, los hijos{H1121} de Hatita{H2410}, los hijos{H1121} de Sobai{H7630}; [en] todos{H3605}, ciento{H3967} treinta{H7970} y nueve{H8672}.",
      "43": "Los Nethineos{H5411}: los hijos{H1121} de Siha, los hijos{H1121} de Hasupha{H2817}, los hijos{H1121} de Thabaoth{H2884},",
      "44": "Los hijos{H1121} de Chêros{H7026}, los hijos{H1121} de Siaa{H5517}, los hijos{H1121} de Phadón{H6303};",
      "45": "Los hijos{H1121} de Lebana{H3838}, los hijos{H1121} de Hagaba{H2286}, los hijos{H1121} de Accub{H6126};",
      "46": "Los hijos{H1121} de Hagab{H2285}, los hijos{H1121} de Samlai{H8073}, los hijos{H1121} de Hanán{H2605};",
      "47": "Los hijos{H1121} de Giddel{H1435}, los hijos{H1121} de Gaher{H1515}, los hijos{H1121} de Reaía{H7211};",
      "48": "Los hijos{H1121} de Resin{H7526}, los hijos{H1121} de Necoda{H5353}, los hijos{H1121} de Gazam{H1502};",
      "49": "Los hijos{H1121} de Uzza{H5798}, los hijos{H1121} de Phasea{H6454}, los hijos{H1121} de Besai{H1153};",
      "50": "Los hijos{H1121} de Asena{H619}, los hijos{H1121} de Meunim{H4586}, los hijos{H1121} de Nephusim{H5300};",
      "51": "Los hijos{H1121} de Bacbuc{H1227}, los hijos{H1121} de Hacusa{H2709}, los hijos{H1121} de Harhur{H2744};",
      "52": "Los hijos{H1121} de Basluth{H1213}, los hijos{H1121} de Mehida{H4240}, los hijos{H1121} de Harsa{H2797};",
      "53": "Los hijos{H1121} de Barcos{H1302}, los hijos{H1121} de Sisera{H5516}, los hijos{H1121} de Thema{H8547};",
      "54": "Los hijos{H1121} de Nesía{H5335}, los hijos{H1121} de Hatipha{H2412}.",
      "55": "Los hijos{H1121} de los siervos{H5650} de Salomón{H8010}: los hijos{H1121} de Sotai{H5479}, los hijos{H1121} de Sophereth{H5618}, los hijos{H1121} de Peruda{H6514};",
      "56": "Los hijos{H1121} de Jaala{H3279}, los hijos{H1121} de Darcón{H1874}, los hijos{H1121} de Giddel{H1435};",
      "57": "Los hijos{H1121} de Sephatías{H8203}, los hijos{H1121} de Hatil{H2411}, los hijos{H1121} de Phochêreth-hassebaim{H6380}, los hijos{H1121} de Ami{H532}.",
      "58": "Todos{H3605} los Nethineos{H5411}, é hijos{H1121} de los siervos{H5650} de Salomón{H8010}, trescientos{H7969}{H3967} noventa{H8673} y dos{H8147}.",
      "59": "Y estos{H428} fueron los que subieron{H5927} de Tel-mela{H8528}, Tel-harsa{H8521}, Chêrub{H3743}, Addan{H135}, é Immer{H564}, los cuales no{H3808} pudieron{H3201} mostrar la casa{H1004} de sus{H1992} padres{H1}, ni su{H1992} linaje{H2233}, si{H518} eran de Israel{H3478}:",
      "60": "Los hijos{H1121} de Delaía{H1806}, los hijos{H1121} de Tobías{H2900}, los hijos{H1121} de Necoda{H5353}, seiscientos{H8337}{H3967} cincuenta{H2572} y dos{H8147}.",
      "61": "Y de los hijos{H1121} de los sacerdotes{H3548}: los hijos{H1121} de Abaía{H2252}, los hijos{H1121} de Cos{H6976}, los hijos{H1121} de Barzillai{H1271}, el cual{H834} tomó{H3947} mujer{H802} de las hijas{H1323} de Barzillai{H1271} Galaadita{H1569}, y fué llamado{H7121} del nombre{H8034} de ellas.",
      "62": "Estos{H428} buscaron{H1245} su registro{H3791} de genealogías{H3187}, y no{H3808} fué hallado{H4672}; y fueron echados{H1351} del{H4480} sacerdocio{H3550}.",
      "63": "Y el Tirsatha{H8660} les dijo{H559} que{H834} no{H3808} comiesen{H398} de las cosas más santas{H6944}, hasta{H5704} que{H834} hubiese{H5975} sacerdote{H3548} con Urim{H224} y Thummim{H8550}.",
      "64": "Toda{H3605} la congregación{H6951}, unida{H259} como un [solo hombre], era de cuarenta{H702}{H7239} y dos mil{H505} trescientos{H7969}{H3967} y sesenta{H8346},",
      "65": "Sin{H905} sus siervos{H5650} y siervas{H519}, los cuales{H428} eran siete{H7651} mil{H505} trescientos{H7969}{H3967} treinta{H7970} y siete{H7651}: y tenían doscientos{H3967} cantores{H7891} y cantoras{H7891}.",
      "66": "Sus caballos{H5483} eran setecientos{H7651}{H3967} treinta{H7970} y seis{H8337}; sus mulos{H6505}, doscientos{H3967} cuarenta{H705} y cinco{H2568};",
      "67": "Sus camellos{H1581}, cuatrocientos{H702}{H3967} treinta{H7970} y cinco{H2568}; asnos{H2543}, seis{H8337} mil{H505} setecientos{H7651}{H3967} y veinte{H6242}.",
      "68": "Y algunos de los cabezas{H7218} de los padres{H1}, cuando vinieron{H935} á la casa{H1004} de Jehová{H3068} la cual estaba en Jerusalem{H3389}, ofrecieron voluntariamente{H5068} para la casa{H1004} de Dios{H430}, para levantarla{H5975} en{H5921} su asiento{H4349}.",
      "69": "Según sus fuerzas{H3581} dieron{H5414} al tesorero{H214} de la obra{H4399} sesenta{H8337} y un mil{H505} dracmas de oro{H2091}, y cinco{H2568} mil{H505} libras{H4488} de plata{H3701}, y cien{H3967} túnicas{H3801} sacerdotales{H3548}.",
      "70": "Y habitaron{H3427} los sacerdotes{H3548}, y los Levitas{H3881}, y [los] del{H4480} pueblo{H5971}, y los cantores{H7891}, y los porteros{H7778} y los Nethineos{H5411}, en sus ciudades{H5892}; y todo{H3605} Israel{H3478} en sus ciudades{H5892}."
    },
    "3": {
      "1": "Y LLEGADO el mes{H2320} séptimo{H7637}, y [ya] los hijos{H1121} de Israel{H3478} en las ciudades{H5892}, juntóse{H622} el pueblo{H5971} como un{H259} solo hombre{H376} en{H413} Jerusalem{H3389}.",
      "2": "Entonces se levantó Jesuá{H3442} hijo{H1121} de Josadec{H3136}, y sus hermanos{H251} los sacerdotes{H3548}, y Zorobabel{H2216} hijo{H1121} de Sealthiel{H7597}, y sus hermanos{H251}, y edificaron{H1129} el altar{H4196} del Dios{H430} de Israel{H3478}, para ofrecer{H5927} sobre{H5921} él holocaustos{H5930}, como está escrito{H3789} en la ley{H8451} de Moisés{H4872} varón{H376} de Dios{H430}.",
      "3": "Y asentaron{H3559} el altar{H4196} sobre{H5921} sus basas{H4350}, bien que tenían{H5921} miedo{H367} de los pueblos{H5971} de las tierras{H776}, y ofrecieron{H5927} sobre{H5921} él holocaustos{H5930} á Jehová{H3068}, holocaustos{H5930} á la mañana{H1242} y á la tarde{H6153}.",
      "4": "Hicieron{H6213} asimismo la solemnidad{H2282} de las cabañas{H5521}, como está escrito{H3789}, y holocaustos{H5930} cada día{H3117} por cuenta{H4557}, conforme al rito{H4941}, cada{H1697} cosa en su día{H3117};",
      "5": "Y á más de esto, el holocausto{H5930} continuo{H8548}, y las nuevas{H2320} lunas, y todas{H3605} las fiestas{H4150} santificadas de Jehová{H3068}, y todo{H3605} [sacrificio] espontáneo{H5068}, [toda] ofrenda voluntaria{H5071} á Jehová{H3068}.",
      "6": "Desde el primer{H259} día{H3117} del mes{H2320} séptimo{H7637} comenzaron{H2490} á ofrecer{H5927} holocaustos{H5930} á Jehová{H3068}; mas el templo{H1964} de Jehová{H3068} no{H3808} estaba aún fundado{H3245}.",
      "7": "Y dieron{H5414} dinero{H3701} á los carpinteros{H2672} y oficiales{H2796}; asimismo comida{H3978} y bebida{H4960} y aceite{H8081} á los Sidonios{H6722} y Tirios{H6876}, para que trajesen{H935} madera{H6086} de cedro{H730} del Líbano{H3844} á la mar{H3220} de Joppe{H3305}, conforme á la voluntad{H7558} de Ciro{H3566} rey{H4428} de Persia{H6539} acerca de{H5921} esto.",
      "8": "Y en el año{H8141} segundo{H8145} de su venida{H935} á{H413} la casa{H1004} de Dios{H430} en Jerusalem{H3389}, en el mes{H2320} segundo{H8145}, comenzaron{H2490} Zorobabel{H2216} hijo{H1121} de Sealthiel{H7597}, y Jesuá{H3442} hijo{H1121} de Josadec{H3136}, y los otros{H7605} sus hermanos{H251}, los sacerdotes{H3548} y los Levitas{H3881}, y todos{H3605} los que habían venido{H935} de la cautividad{H7628} á Jerusalem{H3389}; y pusieron{H5975} á los Levitas{H3881} de veinte{H6242} años{H8141} arriba{H4605} para que tuviesen cargo{H5329} de la obra{H4399} de la casa{H1004} de Jehová{H3068}.",
      "9": "Jesuá{H3442} también, sus hijos{H1121} y sus hermanos{H251}, Cadmiel{H6934} y sus hijos{H1121}, hijos{H1121} de Judá{H3063}, como un{H259} [solo hombre] asistían{H5975} para dar priesa{H5329} á{H5921} los que hacían{H6213} la obra{H4399} en la casa{H1004} de Dios{H430}: los hijos{H1121} de Henadad{H2582}, sus hijos{H1121} y sus hermanos{H251}, Levitas{H3881}.",
      "10": "Y cuando los albañiles{H1129} del templo{H1964} de Jehová{H3068} echaban los cimientos{H3245}, pusieron{H5975} á los sacerdotes{H3548} vestidos{H3847} de [sus ropas], con trompetas{H2689}, y á Levitas{H3881} hijos{H1121} de Asaph{H623} con címbalos{H4700}, para que alabasen{H1984} á Jehová{H3068}, según{H5921} ordenanza{H3027} de David{H1732} rey{H4428} de Israel{H3478}.",
      "11": "Y cantaban{H6030}, alabando{H1984} y confesando{H3034} á Jehová{H3068}, [y decían]: Porque{H3588} es bueno{H2896}, porque{H3588} para siempre{H5769} es su misericordia{H2617} sobre{H5921} Israel{H3478}. Y todo{H3605} el pueblo{H5971} aclamaba{H7321} con grande{H1419} júbilo{H8643}, alabando{H1984} á Jehová{H3068}, porque{H5921} á la casa{H1004} de Jehová{H3068} se echaba el cimiento{H3245}.",
      "12": "Y muchos{H7227} de los sacerdotes{H3548} y de los Levitas{H3881} y de los cabezas{H7218} de los padres{H1}, ancianos{H2205} que{H834} habían visto{H7200} la casa{H1004} primera{H7223}, viendo fundar{H3245} esta casa{H1004}, lloraban{H1058} en alta{H1419} voz{H6963}, mientras muchos{H7227} [otros] daban grandes{H7311} gritos{H8643} de alegría{H8057}.",
      "13": "Y no{H369} podía discernir el pueblo{H5971} el clamor{H6963} de los gritos{H8643} de alegría{H8057}, de la voz{H6963} del lloro{H1065} del pueblo{H5971}: porque{H3588} clamaba el pueblo{H5971} con grande{H1419} júbilo{H8643}, y oíase{H8085} el ruido{H6963} hasta{H5704} de lejos{H7350}."
    },
    "4": {
      "1": "Y OYENDO{H8085} los enemigos{H6862} de Judá{H3063} y de Benjamín{H1144}, que{H3588} los [venidos] de la cautividad{H1473} edificaban{H1129} el templo{H1964} de Jehová{H3068} Dios{H430} de Israel{H3478},",
      "2": "Llegáronse{H5066} á Zorobabel{H2216}, y á los cabezas{H7218} de los padres{H1}, y dijéronles{H559}: Edificaremos{H1129} con{H5973} vosotros, porque{H3588} como vosotros buscaremos á vuestro Dios{H430}, y á él sacrificamos desde los días{H3117} de Esar-haddón{H634} rey{H4428} de Asiria{H804}, que nos hizo subir{H5927} aquí{H6311}.",
      "3": "Y díjoles{H559} Zorobabel{H2216}, y Jesuá{H3442}, y los demás{H7605} cabezas{H7218} de los padres{H1} de Israel{H3478}: No{H3808} nos conviene edificar con vosotros casa{H1004} á nuestro{H587} Dios{H430}, sino{H3588} que nosotros{H587} solos{H3162} [la] edificaremos{H1129} á Jehová{H3068} Dios{H430} de Israel{H3478}, como nos{H587} mandó{H6680} el rey{H4428} Ciro{H3566}, rey{H4428} de Persia{H6539}.",
      "4": "Mas el pueblo{H5971} de la tierra{H776} debilitaba las manos del pueblo{H5971} de Judá{H3063}, y los arredraban de edificar{H1129}.",
      "5": "Cohecharon además contra{H5921} ellos consejeros{H3289} para disipar su consejo, todo{H3605} el tiempo{H3117} de Ciro{H3566} rey{H4428} de Persia{H6539}, y hasta{H5704} el reinado{H4438} de Darío{H1867} rey{H4428} de Persia{H6539}.",
      "6": "Y en el reinado{H4438} de Assuero{H325}, en el principio{H8462} de su reinado{H4438}, escribieron{H3789} acusaciones{H7855} contra{H5921} los moradores{H3427} de Judá{H3063} y de Jerusalem{H3389}.",
      "7": "Y en días{H3117} de Artajerjes{H783}, Bislam{H1312}, Mitrídates{H4990}, Tabeel{H2870}, y los demás{H7605} sus compañeros{H3674}, escribieron{H3789} á{H5921} Artajerjes{H783} rey{H4428} de Persia{H6539}; y la escritura{H3791} de la carta{H5406} estaba hecha{H3789} en siriaco{H762}, y declarada{H3789} en siriaco{H762}.",
      "8": "Rehum{H7348} canciller{H1169}, y Simsai{H8124} secretario{H5613}, escribieron{H3790} una carta{H104} contra{H5922} Jerusalem{H3390} al rey{H4430} Artajerjes{H783}, como se sigue.",
      "9": "Entonces Rehum{H7348} canciller{H1169}, y Simsai{H8124} secretario{H5613}, y los demás{H7606} sus compañeros{H3675}, los Dineos{H1784}, y los Apharsathachêos{H671}, Thepharleos{H2967}, Apharseos{H670}, los Erchûeos{H756}, los Babilonios{H896}, Susanchêos{H7801}, Dieveos{H1723}, y Elamitas{H5962};",
      "10": "Y los demás{H7606} pueblos{H524} que{H1768} el grande{H7229} y glorioso{H3358} Asnappar{H620} trasportó{H1541}, é hizo habitar{H3488}{H1994} en las ciudades{H7149} de Samaria{H8115}, y los demás{H7606} de la otra parte del río{H5103}, etcétera, [escribieron].",
      "11": "Este es el traslado{H6573} de la carta{H104} que{H1768} enviaron{H7972}: Al{H5922} rey Artajerjes{H783}: Tus siervos{H5649} de la otra parte{H5675} del río{H5103}, etcétera.",
      "12": "Sea notorio{H3046} al rey{H4430}, que{H1768} los Judíos que{H1768} subieron{H5559} de{H4481} ti{H3890} á nosotros{H587}, vinieron{H858} á Jerusalem{H3390}; y edifican{H1124} la ciudad{H7149} rebelde{H4779} y mala, y han erigido los muros{H7792}; y compuesto los fundamentos{H787}.",
      "13": "Ahora{H3705}, notorio{H3046} sea al rey{H4430}, que{H1768} si{H2006} aquella{H1791} ciudad{H7149} fuere reedificada{H1124}, y los muros{H7792} fueren establecidos{H3635}, el tributo{H4061}, pecho{H1093}, y rentas{H1983} no{H3809} darán{H5415}, y el catastro{H674} de lo reyes{H4430} será menoscabado{H5142}.",
      "14": "Ya pues que{H1768} estamos mantenidos de palacio{H1965}, no{H3809} nos es justo{H749} ver el menosprecio{H6173} del rey{H4430}: hemos enviado{H7972} por{H5922} tanto, y hécho[lo] saber{H3046} al rey{H4430},",
      "15": "Para que busque{H1240} en el libro{H5609} de las historias de nuestros padres{H2}; y hallarás{H7912} en el libro{H5609} de las historias, y sabrás{H1768} que esta{H1791} ciudad{H7149} es ciudad{H7149} rebelde{H4779}, y perjudicial{H5142} á los reyes{H4430} y á las provincias{H4083}, y que de{H4481} tiempo{H3118} antiguo forman{H5648} en medio de{H4481} ella rebeliones{H849}; por{H5922} lo que{H1837} esta{H1791} ciudad{H7149} fué destruída{H2718}.",
      "16": "Hacemos saber{H3046} al rey{H4430}, que si{H1768} esta{H2006} ciudad{H1791} fuere{H7149} edificada, y erigidos sus muros{H1837}, la parte allá{H5675} del río{H5103} no{H3809} será tuya.",
      "17": "El rey{H4430} envió{H7972} [esta] respuesta{H6600} á Rehum{H7348} canciller{H1169}, y á Simsai{H8124} secretario{H5613}, y á los demás{H7606} sus compañeros{H3675} que habitan{H3488} en Samaria{H8115}, y á los demás{H7606} de la parte{H5675} allá del río{H5103}: Paz{H8001}, etc.",
      "18": "La carta{H5407} que nos{H1768} enviasteis{H7972} claramente{H6568} fué leída{H7123} delante{H6925} de mí.",
      "19": "Y por{H4481} mí fué dado{H7761} mandamiento{H2942}, y buscaron{H1240}, y hallaron{H7912} que{H1768} aquella{H1791} ciudad{H7149} de{H4481} tiempo{H3118} antiguo{H5957} se levanta{H5376} contra{H5922} los reyes{H4430}, y se rebela{H4776}, y se forma{H5648} en ella sedición{H849}:",
      "20": "Y que reyes{H4430} fuertes{H8624} hubo{H1934} en{H5922} Jerusalem{H3390}, quienes señorearon{H7990} en{H5922} todo{H3606} [lo que está] á la parte allá{H5675} del río{H5103}; y que tributo{H4061}, y pecho, y rentas{H1983} se les daba.",
      "21": "Ahora{H3705} [pues] dad{H7761} orden{H2942} que cesen{H989} aquellos{H479} hombres{H1400}, y no{H3809} sea esa{H1791} ciudad{H7149} edificada, hasta{H5705} que por{H4481} mí sea dado{H7761} mandamiento{H2941}.",
      "22": "Y mirad{H2095} bien que no hagáis error{H7960} en{H5922} esto{H1836}: ¿por qué{H4101} habrá de crecer{H7680} el daño{H2257} para perjuicio{H5142} de los reyes{H4430}?",
      "23": "Entonces{H116}, cuando{H4481}{H1768} el traslado{H6573} de la carta{H5407} del rey{H4430} Artajerjes{H783} fué leído{H7123} delante{H6925} de Rehum{H7348}, y de Simsai{H8124} secretario{H5613}, y sus compañeros{H3675}, fueron{H236} prestamente{H924} á Jerusalem{H3390} á{H5922} los Judíos{H3062}, é hiciéronles cesar{H989} con poder{H153} y fuerza{H2429}.",
      "24": "Cesó{H989} entonces{H116} la obra{H5673} de la casa{H1005} de Dios{H426}, la cual estaba en Jerusalem{H3390}: y cesó{H989} hasta{H5705} el año{H8140} segundo{H8648} del reinado{H4437} de Darío{H1868} rey{H4430} de Persia{H6540}."
    },
    "5": {
      "1": "Y PROFETIZARON{H5013} Haggeo{H2292} profeta, y Zacarías{H2148} hijo{H1247} de Iddo{H5714}, profetas{H5029}, á los Judíos{H3062} que{H1768} estaban en Judá{H3061} y en Jerusalem{H3390} [yendo] en nombre{H8036} del Dios{H426} de Israel{H3479} á ellos.",
      "2": "Entonces{H116} se levantaron{H6966} Zorobabel{H2217} hijo{H1247} de Sealthiel{H7598}, y Jesuá{H3443}{H3442} hijo{H1247} de Josadec{H3136}; y comenzaron{H8271} á edificar la casa{H1005} de Dios{H426} que{H1768} estaba en Jerusalem{H3390}; y con ellos{H5974} los profetas{H5029} de Dios{H426} que{H1768} les ayudaban{H5583}.",
      "3": "En aquel tiempo{H2166} vino{H858} á{H5922} ellos Tatnai{H8674}, capitán{H6347} de la parte allá{H5675} del río{H5103}, y Sethar-boznai{H8370} y sus compañeros{H3675}, y dijéronles{H560} así{H3652}: ¿Quién os dió mandamiento{H2942} para edificar{H1124} esta{H1837} casa{H1005}, y restablecer estos{H1836} muros{H846}?",
      "4": "Entonces les{H581} dijimos{H560} en orden á esto cuáles{H4479} eran{H581} los nombres{H8036} de los varones{H1400} que{H1768} edificaban{H1124} este{H1836} edificio{H1147}.",
      "5": "Mas los ojos{H5870} de su Dios{H426} fueron{H1934} sobre{H5922} los ancianos{H7868} de los Judíos{H3062}, y no{H3809} les hicieron cesar{H989} hasta{H5705} que el negocio{H2941} viniese{H1946} á Darío{H1868}: y entonces{H116} respondieron{H8421} por carta{H5407} sobre{H5922} esto{H1837}.",
      "6": "Traslado de la carta{H104} que{H1768} Tatnai{H8674}, capitán{H6347} de la parte allá{H5675} del río{H5103}, y Sethar-boznai{H8370}, y sus compañeros{H3675} los Apharsachêos{H671}, que{H1768} estaban á la parte allá del río{H5103}, enviaron{H7972} al rey{H4430} Darío{H1868}.",
      "7": "Enviáronle{H7972} carta{H6600}, y de esta manera estaba escrito{H3790} en ella{H1836}. Al rey{H4430} Darío{H1868} toda{H3606} paz{H8001}.",
      "8": "Sea{H1934} notorio{H3046} al rey{H4430}, que{H1768} fuimos{H236} á la provincia{H4083} de Judea{H3061}, á la casa{H1005} del gran{H7229} Dios{H426}, la cual{H1932} se edifica{H1124} de piedra{H69} de mármol{H1560}; y los maderos{H636} son puestos{H7761} en las paredes{H3797}, y la obra{H5673} se hace{H5648} apriesa{H629}, y prospera{H6744} en sus manos{H3028}.",
      "9": "Entonces{H116} preguntamos{H7593} á los ancianos{H7868}, diciéndoles{H560} así{H3660}: ¿Quién{H4479} os dió{H7761} mandamiento{H2942} para edificar{H1124} esta{H1836} casa{H1005}, y para restablecer estos{H1836} muros{H846}?",
      "10": "Y también{H638} les preguntamos{H7593} sus nombres{H8036} para hacértelo saber{H3046}, para escribir{H3790}[te] los nombres{H8036} de los varones que{H1768} estaban por cabezas de ellos.",
      "11": "Y respondiéronnos, diciendo{H560} así{H3660}: Nosotros{H586} somos siervos{H5649} del Dios{H426} del cielo{H8065} y de la tierra{H772}, y reedificamos{H1124} la casa{H1005} que{H1768} ya muchos{H7690} años{H8140} antes había sido edificada{H1124}, la cual{H1934} edificó{H1124} y fundó{H3635} el gran{H7229} rey{H4430} de Israel{H3479}.",
      "12": "Mas{H3861} después{H4481} que{H1768} nuestros{H586} padres{H2} ensañaron al Dios{H426} de los cielos{H8065}, él los{H1994} entregó{H3052} en mano{H3028} de Nabucodonosor{H5020} rey{H4430} de Babilonia{H895}, Caldeo{H3679}, el cual destruyó{H5642} esta{H1836} casa{H1005}, é hizo trasportar{H1541} el pueblo{H5972} á Babilonia{H895}.",
      "13": "Empero el primer año{H8140} de Ciro{H3567} rey{H4430} de Babilonia{H895}, el [mismo] rey{H4430} Ciro{H3567} dió{H7761} mandamiento{H2942} para que esta{H1836} casa{H1005} de Dios{H426} fuese edificada{H1124}.",
      "14": "Y también{H638} los vasos{H3984} de{H1768} oro{H1722} y de{H1768} plata{H3702} de{H1768} la casa{H1005} de{H1768} Dios{H426}, que Nabucodonosor{H5020} había sacado{H5312} del{H4481} templo{H1965} que estaba en Jerusalem{H3390}, y los{H1994} había metido{H2987} en el templo{H1965} de{H1768} Babilonia{H895}, el rey{H4430} Ciro{H3567} los{H1994} sacó{H5312} del{H4481} templo{H1965} de{H1768} Babilonia{H895}, y fueron entregados{H3052} á Sesbassar{H8340}, al cual había puesto{H7761} por gobernador{H6347};",
      "15": "Y le dijo{H560}: Toma{H5376} estos{H412} vasos{H3984}, ve{H236} y ponlos{H5182} en el templo{H1965} que{H1768} está en Jerusalem{H3390}; y la casa{H1005} de Dios{H426} sea edificada en{H5922} su lugar{H870}.",
      "16": "Entonces{H116} este{H1791} Sesbassar{H8340} vino{H858}, y puso{H3052} los fundamentos{H787} de la casa{H1005} de Dios{H426} que{H1768} estaba en Jerusalem{H3390}, y desde{H4481} entonces{H116} hasta{H5705} ahora{H3705} se edifica{H1124}, y aun no{H3809} está acabada{H8000}.",
      "17": "Y ahora{H3705}, si{H2006} al{H5922} rey{H4430} parece bien{H2869}, búsquese{H1240} en la casa{H1005} de los tesoros{H1596} del rey{H4430} que{H1768} está allí{H8536} en Babilonia{H895}, si{H2006} es{H383} así que{H1768} por{H4481} el rey{H4430} Ciro{H3567} había sido dado{H7761} mandamiento{H2942} para edificar esta{H1791} casa{H1005} de Dios{H426} en Jerusalem{H3390}, y envíenos [á decir] la voluntad{H7470} del rey{H4430} sobre{H5922} esto{H1836}."
    },
    "6": {
      "1": "ENTONCES{H116} el rey{H4430} Darío{H1868} dió{H7761} mandamiento{H2942}, y buscaron en la casa{H1005} de los libros, donde{H1768} guardaban{H5182} los tesoros{H1596} allí{H8536} en Babilonia{H895}.",
      "2": "Y fué hallado{H7912} en Achmetta{H307}, en el palacio{H1001} que{H1768} está en la provincia{H4083} de Media{H4076}, un libro{H4040}, dentro del cual{H1459} estaba escrito{H3790} así{H3652}: Memoria{H1799}:",
      "3": "En el año{H8140} primero{H2298} del rey{H4430} Ciro{H3567}, el [mismo] rey{H4430} Ciro{H3567} dió{H7761} mandamiento{H2942} acerca de la casa{H1005} de Dios{H426} que estaba en Jerusalem{H3390}, que fuese la casa{H1005} edificada{H1124} para lugar{H870} en que sacrifiquen{H1684} sacrificios{H1685}, y que sus paredes{H787} fuesen cubiertas{H5446}; su altura{H7314} de sesenta{H8361} codos{H521}, y de sesenta{H8361} codos{H521} su anchura{H6613};",
      "4": "Los órdenes{H5073}, tres{H8532} de piedra{H69} de mármol{H1560}, y un orden{H5073} de madera{H636} nueva{H2323}: y que el gasto{H5313} sea dado{H3052} de la casa del rey{H4430}.",
      "5": "Y también{H638} los vasos{H3984} de oro{H1722} y de plata{H3702} de la casa{H1005} de Dios{H426}, que{H1768} Nabucodonosor{H5020} sacó{H5312} del{H4481} templo{H1965} que{H1768} estaba en Jerusalem{H3390} y los pasó{H2987} á Babilonia{H895}, sean devueltos{H8421} y vayan{H1946} al templo{H1965} que{H1768} está en Jerusalem{H3390}, á su lugar{H870}, y sean puestos{H5182} en la casa{H1005} de Dios{H426}.",
      "6": "Ahora{H3705} pues, Tatnai{H8674}, jefe{H6347} del lado allá{H5675} del río{H5103}, Sethar-boznai{H8370}, y sus compañeros{H3675} los Apharsachêos{H671} que{H1768} estáis á la otra{H5675} parte del río{H5103}, apartaos{H7352} de{H4481} ahí{H8536}.",
      "7": "Dejad{H7662} la obra{H1791} de la casa{H1005} de este Dios{H426} al principal{H6347} de los Judíos{H3062}, y á sus ancianos{H7868}, para que edifiquen la casa{H1005} de este Dios{H426} en{H5922} su lugar{H870}.",
      "8": "Y por{H4481} mí es dado{H7761} mandamiento{H2942} de lo que{H1768} habéis de hacer{H5648} con{H5974} los ancianos{H7868} de estos Judíos{H3062}, para edificar la casa{H1005} de este Dios{H426}: que{H1768} de{H4481} la hacienda{H5232} del rey{H4430}, que{H1768} tiene{H1768} del tributo{H4061} de la parte allá{H5675} del río{H5103}, los gastos{H5313} sean dados{H3052} luego á aquellos varones{H1400}, para que{H1768} no{H3809} cesen.",
      "9": "Y lo que{H4101} fuere necesario{H2818}, becerros{H1123} y carneros{H1798} y corderos{H563}, para holocaustos{H5928} al Dios{H426} del cielo{H8065}, trigo{H2591}, sal{H4416}, vino{H2562} y aceite{H4887}, conforme á lo que{H4101} dijeren{H3983} los sacerdotes{H3549} que{H1768} están en Jerusalem{H3390}, déseles cada un día{H3118} sin{H3809} obstáculo{H7960} alguno;",
      "10": "Para que ofrezcan{H1934}{H7127} olores de holganza{H5208} al Dios{H426} del cielo{H8064}, y oren{H6739} por la vida{H2417} del rey{H4430} y por sus{H1934} hijos{H1123}.",
      "11": "También es dado{H7761} por{H4481} mí mandamiento{H2942}, que{H1768} cualquiera{H3606} que{H1768} mudare{H8133} este{H1836} decreto{H6600}, sea derribado{H5256} un madero{H636} de{H4481} su casa{H1005}, y enhiesto{H2211}, sea colgado{H4223} en{H5922} él: y su casa{H1005} sea hecha{H5648} muladar{H5122} por{H5922} esto{H1836}.",
      "12": "Y el Dios{H426} que{H1768} hizo habitar{H7932} allí{H8536} su nombre{H8036}, destruya{H4049} todo{H3606} rey{H4430} y pueblo{H5972} que{H1768} pusiere{H7972} su mano{H3028} para mudar{H8133} ó destruir esta{H1791} casa{H1005} de Dios{H433}, la cual{H1768} está en Jerusalem{H3390}. Yo Darío{H1868} puse el decreto{H2942}: sea hecho{H5648} prestamente{H629}.",
      "13": "Entonces{H116} Tatnai{H8674}, gobernador{H6347} del otro{H5675} lado del río{H5103}, y Sethar-boznai{H8370}, y sus compañeros{H3675}, hicieron{H5648} prestamente según{H3660} el rey{H4430} Darío{H1868} había enviado{H7972}.",
      "14": "Y los ancianos{H7868} de los Judíos{H3062} edificaban{H1124} y prosperaban{H6744}, conforme á la profecía{H5017} de Haggeo{H2292} profeta{H5029}, y de Zacarías{H2148} hijo{H1247} de Iddo{H5714}. Edificaron{H1124} pues, y acabaron{H3635}, por{H4481} el mandamiento{H2942} del Dios{H426} de Israel{H3479}, y por{H4481} el mandamiento{H2942} de Ciro{H3567}, y de Darío{H1868}, y de Artajerjes{H783} rey{H4430} de Persia{H6540}.",
      "15": "Y esta{H1837} casa{H1005} fué acabada al tercer{H8532} día{H3118} del mes{H3393} de Adar{H144}, que{H1768} era{H1932} el sexto{H8353} año{H8140} del reinado{H4437} del rey{H4430} Darío{H1868}.",
      "16": "Y los hijos{H1123} de Israel{H3479}, los sacerdotes{H3549} y los Levitas{H3879}, y los demás{H7606} que habían venido{H1123} de la trasportación{H1547}, hicieron{H5648} la dedicación{H2598} de esta{H1836} casa{H1005} de Dios{H426} con gozo{H2305}.",
      "17": "Y ofrecieron{H7127} en la dedicación{H2598} de esta{H1837} casa{H1005} de Dios{H426} cien{H3969} becerros{H8450}, doscientos{H3969} carneros{H1798}, cuatrocientos{H703} corderos{H563}; y machos{H6841} de cabrío{H5796} en expiación{H2402} por{H5922} todo{H3606} Israel{H3479}, doce{H8646}{H6240}, conforme al número{H4510} de las tribus{H7625} de Israel{H3479}.",
      "18": "Y pusieron{H6966} á los sacerdotes{H3549} en sus clases{H4256}, y á los Levitas{H3879} en sus divisiones, sobre la obra{H5673} de Dios{H426} que está en Jerusalem{H3390}, conforme á lo escrito{H3792} en el libro{H5609} de Moisés{H4873}.",
      "19": "Y los{H1121} de la transmigración{H1473} hicieron{H6213} la pascua{H6453} á los catorce{H702} del mes{H2320} primero{H7223}.",
      "20": "Porque{H3588} los sacerdotes{H3548} y los Levitas{H3881} se habían purificado{H2891} á una{H259}; todos{H3605} fueron limpios{H2889}: y sacrificaron{H7819} la pascua{H6453} por todos{H3605} los de la transmigración, y por sus{H1992} hermanos{H251} los sacerdotes{H3548}, y por sí{H1992} mismos.",
      "21": "Y comieron{H398} los hijos{H1121} de Israel{H3478} que habían vuelto{H7725} de la transmigración{H1473}, y todos{H3605} los que se habían apartado{H914} á ellos de la inmundicia de las gentes{H1471} de la tierra{H776}, para buscar{H1875} á Jehová{H3068} Dios{H430} de Israel{H3478}.",
      "22": "Y celebraron{H6213} la solemnidad{H2282} de los panes ázimos{H4682} siete{H7651} días{H3117} con regocijo{H8057}, por cuanto{H3588} Jehová{H3068} los había alegrado{H8055}, y convertido{H5437} el corazón{H3820} del rey{H4428} de Asiria{H804} á ellos, para esforzar{H2388} sus manos{H3027} en la obra{H4399} de la casa{H1004} de Dios{H430}, del Dios{H430} de Israel{H3478}."
    },
    "7": {
      "1": "PASADAS{H310} estas cosas{H1697}, en el reinado{H4438} de Artajerjes{H783} rey{H4428} de Persia{H6539}, Esdras{H5830}, hijo{H1121} de Seraías{H8304}, hijo{H1121} de Azarías{H5838}, hijo{H1121} de Hilcías{H2518},",
      "2": "Hijo{H1121} de Sallum{H7967}, hijo{H1121} de Sadoc{H6659}, hijo{H1121} de Achîtob{H285},",
      "3": "Hijo{H1121} de Amarías{H568}, hijo{H1121} de Azarías{H5838}, hijo{H1121} de Meraioth{H4812},",
      "4": "Hijo{H1121} de Zeraías{H2228}, hijo{H1121} de Uzzi{H5813}, hijo{H1121} de Bucci{H1231},",
      "5": "Hijo{H1121} de Abisue{H50}, hijo{H1121} de Phinees{H6372}, hijo{H1121} de Eleazar{H499}, hijo{H1121} de Aarón{H175}, primer{H7218} sacerdote{H3548}:",
      "6": "Este{H1931} Esdras{H1931} subió{H5927} de Babilonia{H894}, el cual era escriba{H5608} diligente{H4106} en la ley{H8451} de Moisés{H4872}, que{H834} Jehová{H3068} Dios{H430} de Israel{H3478} había dado{H5414}; y concedióle{H5414} el rey{H4428}, según la mano{H3027} de Jehová{H3068} su{H1931} Dios{H430} sobre{H5921} él, todo{H3605} lo que{H834} pidió{H1246}.",
      "7": "Y subieron{H5927} [con él] á{H413} Jerusalem{H3389} de{H4480} los hijos{H1121} de{H4480} Israel{H3478}, y de{H4480} los sacerdotes{H3548}, y Levitas{H3881}, y cantores{H7891}, y porteros{H7778}, y Nethineos{H5411}, en el séptimo{H7651} año{H8141} del rey{H4428} Artajerjes{H783}.",
      "8": "Y llegó{H935} á Jerusalem{H3389} en el mes{H2320} quinto{H2549}, el año{H8141} séptimo{H7637} del rey{H4428}.",
      "9": "Porque{H3588} el [día] primero{H259} del primer{H7223} mes{H2320} fué el principio{H3246} de la partida de Babilonia{H894}, y al primero{H259} del mes{H2320} quinto{H2549} llegó{H935} á{H413} Jerusalem{H3389}, según la buena{H2896} mano{H3027} de su Dios{H430} sobre él{H1931}.",
      "10": "Porque{H3588} Esdras{H5830} había preparado{H3559} su corazón{H3824} para inquirir{H1875} la ley{H8451} de Jehová{H3068}, y para hacer y enseñar{H3925} á Israel{H3478} mandamientos{H2706} y juicios{H4941}.",
      "11": "Y este es el traslado de la carta{H5406} que{H834} dió{H5414} el rey{H4428} Artajerjes{H783} á Esdras{H5830}, sacerdote{H3548} escriba{H5608}, escriba{H5608} de las palabras mandadas{H4687} de Jehová{H3068}, y de sus estatutos{H2706} á Israel{H3478}:",
      "12": "Artajerjes{H783}, rey{H4430} de los reyes{H4430}, á Esdras{H5831} sacerdote{H3549}, escriba{H5613} perfecto de la ley{H1882} del Dios{H426} del cielo{H8065}: Salud, etc.",
      "13": "Por{H4481} mí es dado{H7761} mandamiento{H2942}, que{H1768} cualquiera{H3606} que{H1768} quisiere en mi reino{H4437}, del{H4481} pueblo{H5974} de Israel{H3479} y de sus sacerdotes{H3549} y Levitas{H3879}, ir{H1946} contigo{H5972}{H5974} á Jerusalem{H3390}, vaya{H1946}.",
      "14": "Porque{H3606} de{H4481} parte{H6925} del rey{H4430} y de{H4481} sus siete{H7655} consultores{H3272} eres enviado{H7972} á visitar{H1240} á Judea{H3061} y á Jerusalem{H3390}, conforme á la ley{H1882} de{H4481} tu Dios{H426} que{H1768} está en tu mano{H3028};",
      "15": "Y á llevar{H2987} la plata{H3702} y el oro{H1722} que el rey{H4430} y sus consultores voluntariamente ofrecen{H5069} al Dios{H426} de Israel{H3479}, cuya{H1768} morada{H4907} está en Jerusalem{H3390};",
      "16": "Y toda{H3606} la plata{H3702} y el oro{H1722} que{H1768} hallares{H7912} en toda{H3606} la provincia{H4083} de Babilonia{H895}, con{H5974} las ofrendas{H5069} voluntarias del pueblo{H5972} y de los sacerdotes{H3549}, que de su voluntad ofrecieren{H5069} para la casa{H1005} de su Dios{H426} que{H1768} está en Jerusalem{H3390}.",
      "17": "Comprarás{H7066} pues{H6903} prestamente con esta plata becerros{H8450}, carneros{H1798}, corderos{H563}, con sus presentes{H4504} y sus libaciones{H5261}, y los ofrecerás{H7127} sobre{H5922} el altar{H4056} de la casa{H1005} de vuestro Dios{H426} que está en Jerusalem{H3390}.",
      "18": "Y lo{H4101} que{H1768} á ti y á tus hermanos{H252} pluguiere hacer{H5648} de la otra{H7606} plata{H3702} y oro{H1722}, hacedlo{H5648} conforme á la voluntad{H7470} de vuestro Dios{H426}.",
      "19": "Y los vasos{H3984} que{H1768} te son entregados{H3052} para el servicio{H6402} de la casa{H1005} de tu Dios{H426}, los restituirás{H8000} delante{H6925} de Dios{H426} en Jerusalem{H3390}.",
      "20": "Y lo demás necesario{H5308} para la casa{H1005} de tu Dios{H426} que te fuere menester{H5308} dar{H5415}, daráslo de{H4481} la casa{H1005} de{H4481} los tesoros{H1596} del rey{H4430}.",
      "21": "Y por{H4481} mí el rey{H4430} Artajerjes{H783} es dado{H7761} mandamiento{H2942} á todos{H3606} los tesoreros{H1490} que{H1768} están al otro{H5675} lado del río{H5103}, que{H1768} todo{H3606} lo que{H1768} os demandare Esdras{H5831} sacerdote{H3549}, escriba{H5613} de la ley{H1882} del Dios{H426} del cielo{H8065}, concédase{H5648}[le] luego{H629},",
      "22": "Hasta{H5705} cien{H3969} talentos{H3604} de plata{H3702}, y hasta{H5705} cien{H3969} coros{H3734} de trigo{H2591}, y hasta{H5705} cien{H3969} batos{H1325} de vino{H2562}, y hasta{H5705} cien{H3969} batos{H1325} de aceite{H4887}; y sal{H4416} sin{H3809} tasa.",
      "23": "Todo{H3606} lo que es mandado{H2941} por{H4481} el Dios{H426} del cielo{H8065}, sea hecho{H5648} prestamente para la casa{H1005} del Dios{H426} del cielo{H8065}: pues{H1768}, ¿por{H4481} qué{H4101} habría de ser su ira{H7109} contra{H5922} el reino{H4437} del rey{H4430} y de sus{H1934} hijos{H1123}?",
      "24": "Y á vosotros os hacemos saber{H3046}, que{H1768} á todos{H3606} los sacerdotes{H3549} y Levitas{H3879}, cantores{H2171}, porteros{H8652}, Nethineos{H5412} y ministros{H6399} de la casa{H1005} de Dios{H426}, ninguno{H3809} pueda imponerles{H7412} tributo{H4061}, ó pecho{H1093}, ó renta{H1983}.",
      "25": "Y tú{H607}, Esdras{H5831}, conforme á la sabiduría{H2452} de tu Dios{H426} que{H1768} tienes, pon{H4483} jueces{H8200} y gobernadores{H1778}, que{H1768} gobiernen{H1934} á todo{H3606} el pueblo{H5972} que{H1768} está del otro{H5675} lado del río{H5103}, á todos{H3606} los que{H1768} tienen noticia de las leyes{H1882} de tu Dios{H426}; y al que{H1768} no{H3809} la tuviere, le enseñaréis.",
      "26": "Y cualquiera{H3606} que{H1768} no{H3809} hiciere{H5648} la ley{H1882} de tu Dios{H426}, y la ley{H1882} del rey{H4430}, prestamente sea juzgado{H1780}, ó á muerte{H4193}, ó á desarraigo, ó á pena{H6065} de la hacienda, ó á prisión{H613}.",
      "27": "Bendito{H1288} Jehová{H3068}, Dios{H430} de nuestros{H587} padres{H1}, que{H834} puso{H5414} tal cosa{H2063} en el corazón{H3820} del rey{H4428}, para honrar{H6286} la casa{H1004} de Jehová{H3068} que{H834} está en Jerusalem{H3389}.",
      "28": "E inclinó{H5186} hacia{H5921} mí{H589} [su] misericordia{H2617} delante{H6440} del rey{H4428} y de sus consultores{H3289}, y de todos{H3605} los príncipes{H8269} poderosos del rey{H4428}. Y yo{H589}, confortado{H2388} según la mano{H3027} de mi{H589} Dios{H3068}{H430} sobre{H5921} mí{H589}, junté los principales{H7218} de Israel{H3478} para que subiesen{H5927} conmigo{H5973}."
    },
    "8": {
      "1": "Y ESTOS{H428} son los cabezas{H7218} de sus familias, y genealogía{H3187} de aquellos que subieron{H5927} conmigo{H5973} de Babilonia{H894}, reinando{H4438} el rey{H4428} Artajerjes{H783}:",
      "2": "De los hijos{H1121} de Phinees{H6372}, Gersón{H1648}; de los hijos{H1121} de Ithamar{H385}, Daniel{H1840}; de los hijos{H1121} de David{H1732}, Hattus{H2407};",
      "3": "De los hijos{H1121} de Sechânías{H7935} y de los hijos{H1121} de Pharos{H6551}, Zacarías{H2148}, y con{H5973} él, en la línea{H3187} de varones{H2145}, ciento{H3967} y cincuenta{H2572};",
      "4": "De los hijos{H1121} de Pahath-moab{H6355}, Elioenai{H454}, hijo{H1121} de Zarahi{H2228}, y con{H5973} él doscientos{H3967} varones{H2145};",
      "5": "De los hijos{H1121} de Sechânías{H7935}, el hijo{H1121} de Jahaziel{H3166}, y con{H5973} él trescientos{H7969}{H3967} varones{H2145};",
      "6": "De los hijos{H1121} de Adín{H5720}, Ebed{H5651}, hijo{H1121} de Jonathán{H3129}, y con{H5973} él cincuenta{H2572} varones{H2145};",
      "7": "De los hijos{H1121} de Elam{H5867}, Isaía{H3470}, hijo{H1121} de Athalías{H6271}, y con{H5973} él setenta{H7657} varones{H2145};",
      "8": "Y de los hijos{H1121} de Sephatías{H8203}, Zebadías{H2069}, hijo{H1121} de Michâel{H4317}, y con{H5973} él ochenta{H8084} varones{H2145};",
      "9": "De los hijos{H1121} de Joab{H3097}, Obadías{H5662}, hijo{H1121} de Jehiel{H3171}, y con{H5973} él doscientos{H3967} diez y ocho{H8083} varones{H2145};",
      "10": "Y de los hijos{H1121} de Solomith{H8019}, el hijo{H1121} de Josiphías{H3131}, y con{H5973} él ciento{H3967} y sesenta{H8346} varones{H2145};",
      "11": "Y de los hijos{H1121} de Bebai{H893}, Zacarías{H2148}, hijo{H1121} de Bebai{H893}, y con{H5973} él veintiocho{H6242}{H8083} varones{H2145};",
      "12": "Y de los hijos{H1121} de Azgad{H5803}, Johanán{H3110}, hijo{H1121} de Catán{H6997}, y con{H5973} él ciento{H3967} y diez{H6235} varones{H2145};",
      "13": "Y de los hijos{H1121} de Adonicam{H140}, los postreros{H314}, cuyos nombres{H8034} son estos{H428}, Eliphelet{H467}, Jeiel{H3273}, y Semaías{H8098}, y con{H5973} ellos sesenta{H8346} varones{H2145};",
      "14": "Y de los hijos{H1121} de Bigvai{H902}, Utai{H5793} y Zabud{H2072}, y con{H5973} ellos sesenta{H7657} varones{H2145}.",
      "15": "Y juntélos{H6908} junto{H413} al río{H5104} que viene{H935} á{H413} Ahava{H163}, y reposamos{H2583} allí{H8033} tres{H7969} días{H3117}: y habiendo buscado{H995} entre el pueblo{H5971} y entre los sacerdotes{H3548}, no{H3808} hallé{H4672} allí{H8033} de los hijos{H1121} de Leví{H3878}.",
      "16": "Entonces despaché{H7971} á Eliezer{H461}, y á Ariel{H740}, y á Semaías{H8098}, y á Elnathán{H494}, y á Jarib{H3402}, y á Elnathán{H494}, y á Nathán{H494}, y á Zacarías{H2148}, y á Mesullam{H4918}, principales{H7218}; asimismo á Joiarib{H3114} y á Elnathán{H494}, hombres doctos{H995};",
      "17": "Y enviélos{H3318} á Iddo{H112}, jefe{H7218} en el lugar{H4725} de Casipia{H3703}, y puse{H7760} en boca{H6310} de ellos las palabras{H1697} que habían de hablar{H1696} á Iddo{H112}, y á sus hermanos{H251} los Nethineos{H5411} en el lugar{H4725} de Casipia{H3703}, para que nos trajesen{H935} ministros{H8334} para la casa{H1004} de nuestro{H587} Dios{H430}.",
      "18": "Y trajéronnos, según la buena{H2896} mano{H3027} de nuestro{H587} Dios{H430} sobre{H5921} nosotros{H587}, un varón{H376} entendido{H7922} de los hijos{H1121} de Mahalí, hijo{H1121} de Leví{H3878}, hijo{H1121} de Israel{H3478}; y á Serabías{H8274} con sus hijos{H1121} y sus hermanos{H251}, dieciocho{H8083};",
      "19": "Y á Hasabías{H2811}, y con{H853} él á Isaía{H3470} de los hijos{H1121} de Merari{H4847}, á sus hermanos{H251} y á sus hijos{H1121}, veinte{H6242};",
      "20": "Y de{H4480} los Nethineos{H5411}, á quienes David{H1732} con los príncipes{H8269} puso{H5414} para el ministerio{H5656} de{H4480} los Levitas{H3881}, doscientos{H3967} y veinte{H6242} Nethineos{H5411}: todos{H3605} los cuales fueron declarados{H5344} por sus nombres{H8034}.",
      "21": "Y publiqué{H7121} ayuno{H6685} allí{H8033} junto{H5921} al río{H5104} de Ahava{H163}, para afligirnos{H6031} delante{H6440} de nuestro{H587} Dios{H430}, para solicitar{H1245} de{H4480} él camino{H1870} derecho{H3477} para nosotros{H587}, y para nuestros{H587} niños{H2945}, y para toda{H3605} nuestra{H587} hacienda{H7399}.",
      "22": "Porque{H3588} tuve vergüenza{H954} de pedir{H7592} al rey{H4428} tropa{H2428} y gente de á caballo{H6571} que nos{H587} defendiesen{H5826} del{H4480} enemigo{H341} en el camino{H1870}: porque{H3588} habíamos hablado{H559} al rey{H4428}, diciendo{H559}: La mano{H3027} de nuestro{H587} Dios{H430} es para bien{H2896} sobre{H5921} todos{H3605} los que{H6571} le buscan{H5800}; mas{H1245} su fortaleza{H5797} y su furor{H639} sobre{H5921} todos{H3605} los que{H6571} le dejan{H5800}.",
      "23": "Ayunamos{H6684} pues, y pedimos{H1245} á nuestro{H587} Dios{H430} sobre{H5921} esto{H2063}, y él nos fué propicio{H6279}.",
      "24": "Aparté{H914} luego doce{H8147}{H6240} de los principales{H8269} de los sacerdotes{H3548}, á Serebías{H8274} y á Hasabías{H2811}, y con{H5973} ellos diez{H6235} de sus hermanos{H251};",
      "25": "Y peséles{H8254} la plata{H3701}, y el oro{H2091}, y los vasos{H3627}, la ofrenda{H8641} que para la casa{H1004} de nuestro{H587} Dios{H430} habían ofrecido{H7311} el rey{H4428}, y sus consultores, y sus príncipes{H8269}, y todos los que se hallaron en Israel{H3478}.",
      "26": "Pesé{H8254} pues en{H5921} manos{H3027} de ellos seiscientos{H8337}{H3967} y cincuenta{H2572} talentos{H3603} de plata{H3701}, y vasos{H3627} de plata{H3701} por cien{H3967} talentos{H3603}, y cien{H3967} talentos{H3603} de oro{H2091};",
      "27": "Además veinte{H6242} tazones{H3713} de oro{H2091}, de mil{H505} dracmas{H150}; y dos{H8147} vasos{H3627} de metal{H5178} limpio{H6668} muy bueno{H2896}, preciados como el oro{H2091}.",
      "28": "Y díjeles: Vosotros{H859} sois consagrados{H6944} á Jehová{H3068}, y santos{H6944} los vasos{H3627}; y la plata{H3701} y el oro{H2091} ofrenda voluntaria{H5071} á Jehová{H3068}, Dios{H430} de nuestros padres{H1}.",
      "29": "Velad, y guardadlos{H8104}, hasta{H5704} que los peséis{H8254} delante{H6440} de los príncipes{H8269} de los sacerdotes{H3548} y Levitas{H3881}, y de los jefes{H8269} de los padres{H1} de Israel{H3478} en Jerusalem{H3389}, en las cámaras{H3957} de la casa{H1004} de Jehová{H3068}.",
      "30": "Los sacerdotes{H3548} pues y Levitas{H3881} recibieron{H6901} el peso{H4948} de la plata{H3701} y del oro{H2091} y de los vasos{H3627}, para traerlo{H935} á Jerusalem{H3389} á la casa{H1004} de nuestro{H587} Dios{H430}.",
      "31": "Y partimos{H5265} del río{H5104} de Ahava{H163} el doce{H8147}{H6240} del mes{H2320} primero{H7223}, para ir{H3212} á Jerusalem{H3389}: y la mano{H3027} de nuestro{H587} Dios{H430} fué sobre{H5921} nosotros{H587}, el cual nos{H587} libró{H5337} de mano{H3709} de enemigo{H341} y de asechador{H693} en{H5921} el camino{H1870}.",
      "32": "Y llegamos{H935} á Jerusalem{H3389}, y reposamos{H3427} allí{H8033} tres{H7969} días{H3117}.",
      "33": "Al cuarto{H7243} día{H3117} fué luego pesada{H8254} la plata{H3701}, y el oro{H2091}, y los vasos{H3627}, en la casa{H1004} de nuestro{H587} Dios{H430}, por{H5921} mano{H3027} de Meremoth{H4822} hijo{H1121} de Urías{H223} sacerdote{H3548}, y con{H5973} él Eleazar{H499} hijo{H1121} de Phinees{H6372}; y con{H5973} ellos Jozabad{H3107} hijo{H1121} de Jesuá{H3442}, y Noadías{H5129} hijo{H1121} de Binnui{H1131}, Levitas{H3881};",
      "34": "Por cuenta{H4557} y por peso{H4948} todo{H3605}: y se apuntó{H3789} todo{H3605} aquel peso{H4948} en aquel tiempo{H6256}.",
      "35": "Los que habían venido{H935} de la cautividad{H1473}, los hijos{H1121} de la transmigración{H7628}, ofrecieron holocaustos{H7126} al{H5930} Dios{H430} de Israel{H3478}, doce{H8147}{H6240} becerros{H6499} por{H5921} todo{H3605} Israel{H3478}, noventa{H8673} y seis{H8337} carneros{H352}, setenta{H7657} y siete{H7651} corderos{H3532}, doce{H8147}{H6240} machos cabríos{H6842} por{H5921} expiación{H2403}: todo{H3605} en holocausto{H5930} á Jehová{H3068}.",
      "36": "Y dieron{H5414} los despachos{H1881} del rey{H4428} á sus gobernadores{H323} y capitanes{H6346} del otro lado{H5676} del río{H5104}, los cuales favorecieron{H5375} al pueblo{H5971} y á la casa{H1004} de Dios{H430}."
    },
    "9": {
      "1": "Y ACABADAS{H3615} estas{H428} cosas, los príncipes{H8269} se llegaron{H5066} á{H413} mí, diciendo{H559}: El pueblo{H5971} de Israel{H3478}, y los sacerdotes{H3548} y Levitas{H3881}, no{H3808} se han apartado de los pueblos{H5971} de las tierras{H776}, de los Cananeos{H3669}, Hetheos{H2850}, Pherezeos{H6522}, Jebuseos{H2983}, Ammonitas{H5984}, y Moabitas{H4125}, Egipcios{H4713}, y Amorrheos{H567}, [haciendo] conforme á sus abominaciones{H8441}.",
      "2": "Porque{H3588} han tomado{H5375} de sus{H1992} hijas{H1323} para sí{H1992} y para sus{H1992} hijos{H1121}, y la simiente{H2233} santa{H6944} ha sido mezclada{H6148} con los pueblos{H5971} de las tierras{H776}; y la mano{H3027} de los príncipes{H8269} y de los gobernadores{H5461} ha sido{H1961} la primera{H7223} en esta prevaricación{H4604}.",
      "3": "Lo cual oyendo yo, rasgué{H7167} mi vestido{H899} y mi manto{H4598}, y arranqué{H4803} de los cabellos{H8181} de mi cabeza{H7218} y de mi barba{H2206}, y sentéme{H3427} atónito{H8074}.",
      "4": "Y juntáronse{H622} á mí todos{H3605} los temerosos de las palabras{H1697} del Dios{H430} de Israel{H3478}, á causa de{H5921} la prevaricación{H4604} de los de la transmigración{H1473}; mas yo{H589} estuve{H3427} sentado atónito{H8074} hasta{H5704} el sacrificio{H4503} de la tarde{H6153}.",
      "5": "Y al sacrificio{H4503} de la tarde{H6153} levantéme{H6965} de mi aflicción{H8589}; y habiendo rasgado mi vestido{H899} y mi manto, postréme{H3766} de rodillas{H5921}, y extendí{H6566} mis palmas{H3709} á{H413} Jehová{H3068} mi Dios{H430};",
      "6": "Y dije{H559}: Dios{H430} mío, confuso{H3637} y avergonzado{H954} estoy para levantar{H7311}, oh Dios{H430} mío, mi rostro{H6440} á{H413} ti: porque{H3588} nuestras{H587} iniquidades{H5771} se han multiplicado{H7235} sobre nuestra cabeza{H7218}, y nuestros{H587} delitos{H819} han crecido{H1431} hasta{H5704} el cielo{H8064}.",
      "7": "Desde los días{H3117} de nuestros{H587} padres{H1} hasta{H5704} este día{H3117} estamos en grande{H1419} culpa{H819}; y por nuestras{H587} iniquidades{H5771} nosotros{H587}, nuestros{H587} reyes{H4428}, y nuestros{H587} sacerdotes{H3548}, hemos sido entregados{H5414} en manos{H3027} de los reyes{H4428} de las tierras{H776}, á cuchillo{H2719}, á cautiverio{H7628}, y á robo{H961}, y á confusión de rostro{H6440}, como hoy día{H3117}.",
      "8": "Y ahora{H6258} como por un breve{H4592} momento{H7281} fué{H1961} la misericordia{H8467} de Jehová{H3068} nuestro{H587} Dios{H430}, para hacer que nos quedase un resto{H7604} libre{H6413}, y para darnos{H5414} estaca en el lugar{H4725} de su santuario{H6944}, á fin de alumbrar{H215} nuestros{H587} ojos{H5869} nuestro{H587} Dios{H430}, y darnos{H5414} una poca de vida{H4241} en nuestra{H587} servidumbre{H5659}.",
      "9": "Porque{H3588} siervos{H5650} éramos: mas en nuestra{H587} servidumbre{H5659} no{H3808} nos{H587} desamparó nuestro{H587} Dios{H430}, antes inclinó{H5186} sobre{H5921} nosotros{H587} misericordia{H2617} delante{H6440} de los reyes{H4428} de Persia{H6539}, para que [se] nos{H587} diese{H5414} vida{H4241} para alzar la casa{H1004} de nuestro{H587} Dios{H430}, y para hacer restaurar{H5975} sus asolamientos{H2723}, y para darnos{H5414} vallado{H1447} en Judá{H3063} y en Jerusalem{H3389}.",
      "10": "Mas ahora{H6258}, ¿qué{H4100} diremos{H559}, oh Dios{H430} nuestro{H587}, después{H310} de esto{H2063}? porque{H3588} nosotros hemos dejado{H5800} tus mandamientos{H4687},",
      "11": "Los cuales prescribiste{H6680} por mano{H3027} de tus{H859} siervos{H5650} los profetas{H5030}, diciendo{H559}: La tierra{H776} á la cual{H834} entráis{H935} para poseerla{H3423}, tierra{H776} inmunda{H5079} es á causa de la inmundicia{H5079} de los pueblos{H5971} de aquellas regiones{H776}, por las abominaciones{H8441} de que{H834} la{H1931} han henchido{H4390} de uno{H6310} á otro extremo{H6310} con su inmundicia{H2932}.",
      "12": "Ahora{H6258} pues, no{H408} daréis{H5414} vuestras hijas{H1323} á los hijos{H1121} de ellos, ni{H408} sus hijas{H1323} tomaréis{H5375} para vuestros hijos{H1121}, ni{H3808} procuraréis{H1875} su paz{H7965} ni{H3808} su bien{H2896} para siempre{H5769}; para que seáis corroborados{H2388}, y comáis{H398} el bien{H2896} de la tierra{H776}, y la dejéis{H5414} por heredad{H3423} á vuestros hijos{H1121} para{H5704} siempre{H5769}.",
      "13": "Mas después{H310} de todo{H3605} lo que nos{H5921} ha sobrevenido{H935} á causa de nuestras{H587} malas{H7451} obras{H4639}, y á causa de nuestro{H587} grande{H1419} delito{H819}; ya que{H3588} tú{H859}, Dios{H430} nuestro{H587}, estorbaste{H2820} que fuésemos oprimidos bajo de nuestras{H587} iniquidades{H5771}, y nos diste{H5414} este{H2063} tal efugio;",
      "14": "¿Hemos de volver{H7725} á infringir{H6565} tus mandamientos{H4687}, y á emparentar{H2859} con los pueblos{H5971} de estas abominaciones{H8441}? ¿No{H3808} te ensañarías contra nosotros{H587} hasta{H5704} consumirnos{H3615}, sin{H369} que quedara resto{H7611} ni escapatoria{H6413}?",
      "15": "Jehová{H3068}, Dios{H430} de Israel{H3478}, tú eres{H859} justo{H6662}: pues que{H3588} hemos quedado{H7604} algunos salvos, como este día{H3117}, henos aquí delante{H6440} de ti{H587} en nuestros{H859} delitos{H819}; porque{H3588} no{H369} es posible subsistir{H5975} en tu presencia{H6440} á causa{H859} de esto."
    },
    "10": {
      "1": "Y ORANDO Esdras{H5830} y confesando, llorando{H1058} y postrándose{H5307} delante{H6440} de la casa{H1004} de Dios{H430}, juntóse{H6908} á{H413} él una muy{H3966} grande{H7227} multitud{H6951} de Israel{H3478}, hombres{H582} y mujeres{H802} y niños{H3206}; y{H3588} lloraba{H1058} el pueblo{H5971} con gran{H7235} llanto{H7235}.",
      "2": "Entonces respondió{H6030} Sechânías{H7935} hijo{H1121} de Jehiel{H3171}, de los hijos{H1121} de Elam{H5867}, y dijo{H559} á Esdras{H5830}: Nosotros{H587} hemos prevaricado contra nuestro{H587} Dios{H430}, pues tomamos{H3427} mujeres{H802} extranjeras{H5237} de los pueblos{H5971} de la tierra{H776}: mas hay{H3426} aún{H6258} esperanza{H4723} para Israel{H3478} sobre esto{H2063}.",
      "3": "Ahora{H6258} pues hagamos{H3772} pacto{H1285} con nuestro{H587} Dios{H430}, que echaremos todas{H3605} las mujeres{H802} y los nacidos{H3205} de ellas{H1992}, según el consejo{H6098} del Señor{H113}, y de los que temen{H2730} el mandamiento{H4687} de nuestro{H587} Dios{H430}: y hágase{H6213} conforme á la ley{H8451}.",
      "4": "Levántate{H6965}, porque{H3588} á ti toca el negocio{H1697}, y nosotros{H587} seremos contigo; esfuérzate{H2388}, y ponlo por obra{H6213}.",
      "5": "Entonces se levantó{H6965} Esdras{H5830}, y juramentó{H7650} á los príncipes{H8269} de los sacerdotes{H3548} y de los Levitas{H3881}, y á todo{H3605} Israel{H3478}, que harían{H6213} conforme á esto{H2088}{H1697}; y ellos juraron{H7650}.",
      "6": "Levantóse{H6965} luego Esdras{H5830} de delante{H6440} la casa{H1004} de Dios{H430}, y fuése{H3212} á{H413} la cámara{H3957} de Johanán{H3076} hijo{H1121} de Eliasib{H475}: é ido{H3212} allá{H8033}, no{H3808} comió{H398} pan{H3899} ni{H3808} bebió{H8354} agua{H4325}, porque{H3588} se entristeció{H56} sobre la prevaricación{H4604} de los de la transmigración{H1473}.",
      "7": "E hicieron pasar pregón{H5674} por Judá{H3063} y por Jerusalem{H3389} á todos{H3605} los hijos{H1121} de la transmigración{H1473}, que se juntasen{H6908} en Jerusalem{H3389}:",
      "8": "Y que el que{H834} no{H3808} viniera{H935} dentro de tres{H7969} días{H3117}, conforme al acuerdo{H6098} de los príncipes{H8269} y de los ancianos{H2205}, perdiese{H2763} toda{H3605} su{H1931} hacienda{H7399}, y él fuese apartado{H914} de la compañía{H6951} de los de la transmigración{H1473}.",
      "9": "Así todos{H3605} los hombres{H582} de Judá{H3063} y de Benjamín{H1144} se reunieron{H6908} en Jerusalem{H3389} dentro de tres{H7969} días{H3117}, á los veinte{H6242} del mes{H2320}, el cual era el mes{H2320} noveno{H8671}; y sentóse{H3427} todo{H3605} el pueblo{H5971} en la plaza{H7339} de la casa{H1004} de Dios{H430}, temblando{H7460} con motivo de{H5921} aquel negocio{H1697}, y á causa de{H5921} las lluvias{H1653}.",
      "10": "Y levantóse{H6965} Esdras{H5830} el sacerdote{H3548}, y díjoles{H559}: Vosotros{H859} habéis prevaricado{H4603}, por cuanto tomasteis{H3427} mujeres{H802} extrañas, añadiendo{H3254} [así] sobre{H5921} el pecado{H4603} de Israel{H3478}.",
      "11": "Ahora{H6258} pues, dad{H5414} gloria{H8426} á Jehová{H3068} Dios{H430} de vuestros padres{H1}, y haced{H6213} su voluntad{H7522}, y apartaos{H914} de{H4480} los pueblos{H5971} de{H4480} las tierras{H776}, y de{H4480} las mujeres{H802} extranjeras{H5237}.",
      "12": "Y respondió{H6030} todo{H3605} aquel concurso{H6951}, y dijeron{H559} en alta{H1419} voz{H6963}: Así{H3651} se haga{H6213} conforme á tu palabra{H1697}.",
      "13": "Mas el pueblo{H5971} es mucho{H7227}, y el tiempo{H6256} lluvioso{H1653}, y no{H369} hay fuerza para estar en la calle{H2351}: ni{H3808} la obra{H4399} es de un{H259} día{H3117} ni{H3808} de dos{H8147}, porque{H3588} somos muchos{H7235} los que hemos prevaricado{H6586} en este negocio{H1697}.",
      "14": "Estén ahora nuestros{H587} príncipes{H4994}, los de toda{H3605} la congregación{H6951}; y todos{H3605} aquellos{H3605} que en nuestras{H587} ciudades{H5892} hubieren tomado{H3427} mujeres{H802} extranjeras{H5237}, vengan{H935} á tiempos{H6256} aplazados{H2163}, y con{H5973} ellos los ancianos{H2205} de cada ciudad{H5892}, y los jueces{H8199} de ellas, hasta{H5704} que apartemos{H7725} de{H4480} nosotros el furor{H2740} de{H4480} la ira{H639} de{H4480} nuestro{H587} Dios{H430} sobre esto{H1697}.",
      "15": "Fueron pues puestos{H5975} sobre este negocio{H2063} Jonathán{H3129} hijo{H1121} de Asael{H6214}, y Jaazías hijo{H1121} de Tikvah{H8616}; y Mesullam{H4918} y Sabethai{H7678}, Levitas{H3881}, les ayudaron{H5826}.",
      "16": "E hicieron{H6213} así{H3651} los hijos{H1121} de la transmigración{H1473}. Y apartados{H914} que fueron luego Esdras{H5830} sacerdote{H3548}, y los varones{H582} cabezas{H7218} de familias{H1004} en la casa de sus padres{H1}, todos{H3605} ellos por sus nombres{H8034}, sentáronse{H3427} el primer{H259} día{H3117} del mes{H2320} décimo{H6224} para inquirir{H1875} el negocio{H1697}.",
      "17": "Y concluyeron{H3615}, con todos{H3605} aquellos{H582} que habían tomado{H3427} mujeres{H802} extranjeras{H5237}, al primer{H259} día{H3117} del mes{H2320} primero{H7223}.",
      "18": "Y de los hijos{H1121} de los sacerdotes{H3548} que{H834} habían tomado{H3427} mujeres{H802} extranjeras{H5237}, fueron hallados{H4672} [estos]: De los hijos{H1121} de Jesuá{H3442} hijo{H1121} de Josadec{H3136}, y de sus hermanos{H251}: Maasías{H4641}, y Eliezer{H461}, y Jarib{H3402}, y Gedalías{H1436};",
      "19": "Y dieron{H5414} su mano{H3027} [en promesa] de echar sus mujeres{H802}, y [ofrecieron] como culpados un carnero{H352} de los rebaños{H6629} por su delito{H819}.",
      "20": "Y de los hijos{H1121} de Immer{H564}: Hanani{H2607} y Zebadías{H2069}.",
      "21": "Y de los hijos{H1121} de Harím{H2766}: Maasías{H4641}, y Elías{H452}, y Semeías{H8098}, y Jehiel{H3171}, y Uzzías{H5818}.",
      "22": "Y de los hijos{H1121} de Phasur{H6583}: Elioenai{H454}, Maasías{H4641}, Ismael{H3458}, Nathanael{H5417}, Jozabad{H3107}, y Elasa{H501}.",
      "23": "Y de{H4480} los hijos de{H4480} los Levitas{H3881}: Jozabad{H3107}, y Simi{H8096}, Kelaía{H7041} (este es Kelita{H7042}), Pethaía{H6611}, Judá{H3063} y Eliezer{H461}.",
      "24": "Y de{H4480} los cantores{H7891}, Eliasib{H475}; y de{H4480} los porteros{H7778}: Sellum{H7967}, y Telem{H2928}, y Uri{H221}.",
      "25": "Asimismo de Israel{H3478}: De los hijos{H1121} de Pharos{H6551}: Ramía{H7422} é Izzías{H3150}, y Malchías{H4441}, y Miamim{H4326}, y Eleazar{H499}, y Malchías{H4441}, y Benaías{H1141}.",
      "26": "Y de los hijos{H1121} de Elam{H5867}: Mathanías{H4983}, Zachârías{H2148}, y Jehiel{H3171}, y Abdi{H5660}, y Jeremoth{H3406}, y Elía{H452}.",
      "27": "Y de los hijos{H1121} de Zattu{H2240}: Elioenai{H454}, Eliasib{H475}, Mathanías{H4983}, y Jeremoth{H3406}, y Zabad{H2066}, y Aziza{H5819}.",
      "28": "Y de los hijos{H1121} de Bebai{H893}: Johanán{H3076}, Hananías{H2608}, Zabbai{H893}, Atlai{H6270}.",
      "29": "Y de los hijos{H1121} de Bani{H1137}: Mesullam{H4918}, Malluch{H4409}, y Adaías{H5718}, Jasub{H3437}, y Seal{H7594}, y Ramoth{H3406}.",
      "30": "Y de los hijos{H1121} de Pahath-moab{H6355}: Adna{H5733}, y Chêleal{H3636}, Benaías{H1141}, Maasías{H4641}, Mathanías{H4983}, Besaleel{H1212}, Binnui{H1131} y Manasés{H4519}.",
      "31": "Y de los hijos{H1121} de Harim{H2766}: Eliezer{H461}, Issia{H3449}, Malchîas{H4441}, Semeía{H8098}, Simeón{H8095},",
      "32": "Benjamín{H1144}, Malluch{H4409}, Semarías{H8114}.",
      "33": "De los hijos{H1121} de Hasum{H2828}: Mathenai{H4982}, Mathatha{H4992}, Zabad{H2066}, Eliphelet{H467}, Jeremai{H3413}, Manasés{H4519}, Sami{H8096}.",
      "34": "De los hijos{H1121} de Bani{H1137}: Maadi{H4572}, Amram{H6019} y Uel{H177},",
      "35": "Benaías{H1141}, Bedías{H912}, Chêluhi{H3622},",
      "36": "Vanías{H2057}, Meremoth{H4822}, Eliasib{H475},",
      "37": "Mathanías{H4983}, Mathenai{H4982}, y Jaasai{H3299},",
      "38": "Y Bani{H1137}, y Binnui{H1131}, Simi{H8096},",
      "39": "Y Selemías{H8018} y Nathán{H5416} y Adaías{H5718},",
      "40": "Machnadbai{H4367}, Sasai{H8343}, Sarai{H8298},",
      "41": "Azareel{H5832}, y Selamías{H8018}, Semarías{H8114},",
      "42": "Sallum{H7967}, Amarías{H568}, Joseph{H3130}.",
      "43": "Y de los hijos{H1121} de Nebo: Jehiel{H5015}, Matithías{H3273}, Zabad{H4993}, Zebina{H2066}, Jadau{H2081}, y Joel{H3100}, Benaías{H1141}.",
      "44": "Todos{H3605} estos{H428} habían tomado{H5375} mujeres{H802} extranjeras{H5237}; y había{H3426} mujeres{H802} de ellos{H1992} que habían parido{H7760} hijos{H1121}."
    }
  }
}
