{
  "name": "يەرەمىيانيڭ يىغا-زارلىرى",
  "id": "يەرەمىيانيڭ يىغا-زارلىرى",
  "order": 25,
  "chapters": {
    "3": {
      "2": "مېنى ئۇ ھەيدىۋەتتى، نۇرغا ئەمەس، بەلكى قاراڭغۇلۇققا ماڭدۇردى؛",
      "3": "بەرھەق، ئۇ كۈن بويى قولىنى ماڭا قايتا-قايتا ھۇجۇم قىلدۇردى؛",
      "5": "ئۇ ماڭا مۇھاسىرە قۇردى، ئۆت سۈيى ۋە جاپا بىلەن مېنى قاپسىۋالدى.",
      "6": "ئۇ مېنى ئۆلگىلى ئۇزۇن بولغانلاردەك قاپقاراڭغۇ جايلاردا تۇرۇشقا مەجبۇر قىلدى.",
      "8": "مەن ۋارقىراپ نىدا قىلساممۇ، ئۇ دۇئايىمنى ھېچ ئىشتىمىدى.",
      "9": "ئۇ يوللىرىمنى جىپسىلاشقان تاش تام بىلەن توسۇۋالدى، چىغىر يوللىرىمنى ئەگرى-توقاي قىلىۋەتتى.",
      "11": "مېنى يوللىرىمدىن بۇراپ تېتما-تىتما قىلدى؛ مېنى تۈگەشتۈردى.",
      "12": "ئۇ ئوقياسىنى كېرىپ، مېنى ئوقىنىڭ قارىسى قىلدى.",
      "14": "مەن ئۆز خەلقىمگە رەسۋا ئوبيېكتى، كۈن بويى ئۇلارنىڭ مەسخىرە ناخشىسىنىڭ نىشانى بولدۇم.",
      "15": "ئۇ ماڭا زەردابنى تويغۇچە يۇتقۇزۇپ، كەكرە سۈيىنى تويغۇچە ئىچكۈزدى.",
      "17": "جېنىم تىنچ-خاتىرجەملىكتىن يىراقلاشتۇرۇلدى؛ ئارامبەخشنىڭ نېمە ئىكەنلىكىنى ئۇنتۇپ كەتتىم.",
      "18": "مەن: «دەرمانىم قالمىدى، پەرۋەردىگاردىن ئۈمىدىم قالمىدى» ــ دېدىم.",
      "20": "جېنىم بۇلارنى ھەردائىم ئەسلەۋاتىدۇ، يەرگە كىرىپ كەتكۈدەك بولماقتا.",
      "21": "لېكىن شۇنى كۆڭلۈمگە كەلتۈرۈپ ئەسلەيمەنكى، شۇنىڭ بىلەن ئۈمىد قايتىدىن يانىدۇ، ــ",
      "23": "ئۇلار ھەر سەھەردە يېڭىلىنىدۇ؛ سېنىڭ ھەقىقەت-سادىقلىقىڭ تولىمۇ مولدۇر!",
      "24": "ئۆز-ئۆزۈمگە: «پەرۋەردىگار مېنىڭ نېسىۋەمدۇر؛ شۇڭا مەن ئۇنىڭغا ئۈمىد باغلايمەن» ــ دەيمەن.",
      "26": "پەرۋەردىگارنىڭ نىجاتىنى كۈتۈش، ئۇنى سۈكۈت ئىچىدە كۈتۈش ياخشىدۇر.",
      "27": "ئادەمنىڭ ياش ۋاقتىدا بويۇنتۇرۇقنى كۆتۈرۈشى ياخشىدۇر.",
      "29": "يۈزىنى توپا-تۇپراققا تەگكۈزسۇن، ــ ئېھتىمال، ئۈمىد بولۇپ قالار؟",
      "30": "مەڭزىنى ئۇرغۇچىغا تۇتۇپ بەرسۇن؛ تىل-ئاھانەتلەرنى تويغۇچە ئىشىتسۇن!",
      "32": "ئازار بەرگەن بولسىمۇ، ئۆزگەرمەس مېھرىبانلىقلىرىنىڭ موللۇقى بىلەن ئىچىنى ئاغرىتىدۇ؛",
      "33": "چۈنكى ئۇ ئىنسان بالىلىرىنى خار قىلىشنى ياكى ئازابلاشنى خالىغان ئەمەستۇر.",
      "35": "ھەممىدىن ئالىي بولغۇچىنىڭ ئالدىدا ئادەمنى ئۆز ھەققىدىن مەھرۇم قىلىشقا،",
      "36": "ئىنسانغا ئۆز دەۋاسىدا ئۇۋال قىلىشقا، ــ رەب بۇلارنىڭ ھەممىسىگە گۇۋاھچى ئەمەسمۇ؟",
      "38": "كۈلپەتلەر بولسۇن، بەخت-سائادەت بولسۇن، ھەممىسى ھەممىدىن ئالىي بولغۇچىنىڭ ئاغزىدىن كەلگەن ئەمەسمۇ؟",
      "39": "ئەمدى تىرىك بىر ئىنسان نېمە دەپ ئاغرىنىدۇ، ئادەم بالىسى گۇناھلىرىنىڭ جازاسىدىن نېمە دەپ ۋايسايدۇ؟",
      "41": "قوللىرىمىزنى كۆڭلىمىز بىلەن بىللە ئەرشتىكى تەڭرىگە كۆتۈرەيلى!",
      "42": "بىز ئىتائەتسىزلىك قىلىپ سەندىن يۈز ئۆرىدۇق؛ سەن كەچۈرۈم قىلمىدىڭ.",
      "44": "سەن ئۆزۈڭنى بۇلۇت بىلەن قاپلىغانسەنكى، دۇئا-تىلاۋەت ئۇنىڭدىن ھېچ ئۆتەلمەس.",
      "45": "سەن بىزنى خەلقلەر ئارىسىدا داشقال ۋە نىجاسەت قىلدىڭ.",
      "47": "ئۈستىمىزگە چۈشتى ئالاقزادىلىك ۋە ئورا-تۇزاق، ۋەيرانچىلىق ھەم ھالاكەت.",
      "48": "خەلقىمنىڭ قىزى نابۇت بولغىنى ئۈچۈن، كۆزۈمدىن ياشلار ئۆستەڭ بولۇپ ئاقماقتا.",
      "50": "تاكى پەرۋەردىگار ئاسمانلاردىن تۆۋەنگە نەزەر سېلىپ [ھالىمىزغا] قارىغۇچە.",
      "51": "مېنىڭ كۆزۈم روھىمغا ئازاب يەتكۈزمەكتە، شەھىرىمنىڭ بارلىق قىزلىرىنىڭ ھالى تۈپەيلىدىن.",
      "53": "ئۇلار ئورىدا جېنىمنى ئۈزمەكچى بولۇپ، ئۈستۈمگە تاشنى چۆرىدى.",
      "54": "سۇلار بېشىمدىن تېشىپ ئاقتى؛ مەن: «ئۈزۈپ تاشلاندىم!» ــ دېدىم.",
      "56": "سەن ئاۋازىمنى ئاڭلىدىڭ؛ قۇتۇلدۇرۇشقا نىدايىمغا قۇلىقىڭنى يۇپۇرۇۋالمىغىن!",
      "57": "ساڭا نىدا قىلغان كۈنىدە ماڭا يېقىن كەلدىڭ، «قورقما» ــ دېدىڭ.",
      "59": "ئى پەرۋەردىگار، ماڭا بولغان ئۇۋاللىقنى كۆردۈڭسەن؛ مەن ئۈچۈن ھۆكۈم چىقارغايسەن؛",
      "60": "سەن ئۇلارنىڭ ماڭا قىلغان بارلىق ئۆچمەنلىكلىرىنى، بارلىق قەستلىرىنى كۆردۇڭسەن.",
      "62": "ماڭا قارشى تۇرغانلارنىڭ شىۋىرلاشلىرىنى، ئۇلارنىڭ كۈن بويى كەينىمدىن كۇسۇر-كۇسۇر قىلىشقانلىرىنى ئاڭلىدىڭسەن.",
      "63": "ئولتۇرغانلىرىدا، تۇرغانلىرىدا ئۇلارغا قارىغايسەن! مەن ئۇلارنىڭ [مەسخىرە] ناخشىسى بولدۇم.",
      "65": "ئۇلارنىڭ كۆڭۈللىرىنى كاج قىلغايسەن! بۇ سېنىڭ ئۇلارغا چۈشىدىغان لەنىتىڭ بولىدۇ!",
      "66": "غەزەپ بىلەن ئۇلارنى قوغلىغايسەن، ئۇلارنى پەرۋەردىگارنىڭ ئاسمانلىرى ئاستىدىن يوقاتقايسەن!"
    },
    "5": {
      "1": "بېشىمىزغا چۈشكەنلەرنى ئېسىڭگە كەلتۈرگەيسەن، ئى پەرۋەردىگار؛ قارا، بىزنىڭ رەسۋاچىلىقتا قالغىنىمىزنى نەزىرىڭگە ئالغايسەن!",
      "2": "مىراسىمىز ياتلارغا، ئۆيلىرىمىز ياقا يۇرتلۇقلارغا تاپشۇرۇلدى.",
      "3": "بىز يېتىم-يېسىرلەر، ئاتىسىزلار بولۇپ قالدۇق؛ ئانىلىرىمىزمۇ تۇل قالدى.",
      "4": "ئىچىدىغان سۇنى سېتىۋېلىشىمىز كېرەك؛ ئوتۇننى پەقەت پۇلغا ئالغىلى بولىدۇ.",
      "5": "بىزنى قوغلىغۇچىلار تاپ باستۇرۇپ كېلىۋاتىدۇ؛ ھالسىراپ، ھېچ ئارام تاپالمايمىز.",
      "6": "جان ساقلىغۇدەك بىر چىشلەم ناننى دەپ، مىسىر ھەم ئاسۇرىيەگە قول بېرىپ بويسۇنغانمىز.",
      "7": "ئاتا-بوۋىلىرىمىز گۇناھ سادىر قىلىپ دۇنيادىن كەتتى؛ بىز بولساق، ئۇلارنىڭ قەبىھلىكىنىڭ جازاسىنى كۆتۈرۈشكە قالدۇق.",
      "8": "ئۈستىمىزدىن ھۆكۈم سۈرگۈچىلەر قۇللاردۇر؛ بىزنى ئۇلارنىڭ قولىدىن ئازاد قىلغۇچى يوقتۇر.",
      "9": "دالادا قىلىچ تۈپەيلىدىن، نېنىمىزنى تېپىشقا جېنىمىزنى تەۋەككۇل قىلماقتىمىز.",
      "10": "تېرىمىز تونۇردەك قىزىق، ئاچلىق تۈپەيلىدىن قىزىتما بىزنى باسماقتا.",
      "11": "زىئوندا ئاياللار، يەھۇدا شەھەرلىرىدە پاك قىزلار ئاياغ ئاستى قىلىندى.",
      "12": "ئەمىرلەر قولىدىن دارغا ئېسىپ قويۇلدى؛ ئاقساقاللارنىڭ ھۆرمىتى ھېچ قىلىنمىدى.",
      "13": "ياش يىگىتلەر يارغۇنچاقتا جاپا تارتماقتا، ئوغۇل بالىلىرىمىز ئوتۇن يۈكلەرنى يۈدۈپ دەلدەڭشىپ ماڭماقتا.",
      "14": "ئاقساقاللار شەھەر دەرۋازىسىدا ئولتۇرماس بولدى؛ يىگىتلەر نەغمە-ناۋادىن قالدى.",
      "15": "شاد-خۇراملىق كۆڭلىمىزدىن كەتتى، ئۇسسۇل ئوينىشىمىز ماتەمگە ئايلاندى.",
      "16": "بېشىمىزدىن تاج يىقىلدى؛ ھالىمىزغا ۋاي! چۈنكى بىز گۇناھ سادىر قىلدۇق!",
      "17": "بۇنىڭ تۈپەيلىدىن يۈرەكلىرىمىز مۇجۇلدى؛ بۇلار تۈپەيلىدىن كۆزلىرىمىز قاراڭغۇلاشتى ــ",
      "18": "ــ زىئون تېغىغا قاراپ كۆزلىرىمىز قاراڭغۇلاشتى، چۈنكى ئۇ چۆلدەرەپ كەتتى، چىلبۆرە ئۇنىڭدا پايلاپ يۈرمەكتە.",
      "19": "سەن، ئى پەرۋەردىگار، مەڭگۈگە ھۆكۈم سۈرىسەن؛ تەختىڭ دەۋردىن-دەۋرگە داۋاملىشىدۇ.",
      "20": "سەن نېمىشقا بىزنى دائىم ئۇنتۇيسەن؟ نېمىشقا شۇنچە ئۇزۇنغىچە بىزدىن ۋاز كېچىسەن؟",
      "21": "بىزنى يېنىڭغا قايتۇرغايسەن، ئى پەرۋەردىگار! شۇنداق بولغاندا بىز قايتالايمىز! كۈنلىرىمىزنى قەدىمكىدەك ئەسلىگە كەلتۈرگەيسەن،",
      "22": "ــ ئەگەر سەن بىزنى مۇتلەق چەتكە قاقمىغان بولساڭ، ئەگەر بىزدىن چەكسىز غەزەپلەنمىگەن بولساڭ!"
    }
  }
}
